setup.py
ragames/__init__.py
ragames/ragames.py
ragames.egg-info/PKG-INFO
ragames.egg-info/SOURCES.txt
ragames.egg-info/dependency_links.txt
ragames.egg-info/entry_points.txt
ragames.egg-info/requires.txt
ragames.egg-info/top_level.txt