Metadata-Version: 1.1
Name: ragames
Version: 0.1.0
Summary: List OpenRA games
Home-page: UNKNOWN
Author: bullE
Author-email: bulle.ragl@gmail.com
License: MIT
Keywords: openra
Platform: UNKNOWN
Classifier: Development Status :: 3 - Alpha
Classifier: License :: OSI Approved :: MIT License
Classifier: Programming Language :: Python :: 2.7
